tasksource/__init__.py
tasksource/access.py
tasksource/mtasks.py
tasksource/preprocess.py
tasksource/recast.py
tasksource/tasks.py
tasksource/metadata/__init__.py
tasksource/metadata/bigbench_groups.py
tasksource/metadata/blimp_groups.py
tasksource/metadata/popularity.py
tasksource-0.0.47.dist-info/LICENSE
tasksource-0.0.47.dist-info/METADATA
tasksource-0.0.47.dist-info/WHEEL
tasksource-0.0.47.dist-info/top_level.txt
tasksource-0.0.47.dist-info/RECORD
